biocommons/__init__.py
biocommons-0.0.0.dist-info/DESCRIPTION.rst
biocommons-0.0.0.dist-info/METADATA
biocommons-0.0.0.dist-info/RECORD
biocommons-0.0.0.dist-info/WHEEL
biocommons-0.0.0.dist-info/metadata.json
biocommons-0.0.0.dist-info/top_level.txt
biocommons-0.0.0.dist-info/zip-safe
