Metadata-Version: 2.0
Name: biocommons
Version: 0.0.0
Summary: ensures that the biocommons namespace is correctly declared
Home-page: https://github.com/biocommons/biocommons-namespace-declaration
Author: Reece Hart <reecehart@gmail.com>
Author-email: UNKNOWN
License: UNKNOWN
Platform: UNKNOWN
